Metadata-Version: 2.1
Name: plone.gallery
Version: 1.1.6
Summary: Photo gallery for Plone CMS.
Home-page: https://github.com/plone/plone.gallery
Author: Maik Derstappen
Author-email: md@derico.de
License: GPL version 2
Project-URL: PyPI, https://pypi.python.org/pypi/plone.gallery
Project-URL: Source, https://github.com/plone/plone.gallery
Project-URL: Tracker, https://github.com/plone/plone.gallery/issues
Keywords: Python Plone Photo Gallery
Platform: UNKNOWN
Classifier: Environment :: Web Environment
Classifier: Framework :: Plone
Classifier: Framework :: Plone :: Addon
Classifier: Framework :: Plone :: 5.2
Classifier: Framework :: Plone :: 6.0
Classifier: Programming Language :: Python
Classifier: Programming Language :: Python :: 2.7
Classifier: Programming Language :: Python :: 3.7
Classifier: Programming Language :: Python :: 3.8
Classifier: Programming Language :: Python :: 3.9
Classifier: Programming Language :: Python :: 3.10
Classifier: Operating System :: OS Independent
Classifier: License :: OSI Approved :: GNU General Public License v2 (GPLv2)
Requires-Python: >=2.7,!=3.0.*,!=3.1.*,!=3.2.*,!=3.3.*,!=3.4.*,!=3.5.*,!=3.6.*
Provides-Extra: test
License-File: LICENSE.GPL
License-File: LICENSE.rst
